JaysAppManager/__init__.py
JaysAppManager/functions/ContextMessage.py
JaysAppManager/functions/RunManager.py
JaysAppManager/functions/__init__.py
JaysAppManager/functions/backup.py
JaysAppManager/functions/basemessage.py
JaysAppManager/functions/buffer.py
JaysAppManager/functions/chat_history.py
JaysAppManager/functions/cryptography.py
JaysAppManager/functions/llmredis.py
JaysAppManager/functions/log.py
JaysAppManager/functions/memory.py
JaysAppManager/functions/redis.py
JaysAppManager/functions/register.py
JaysAppManager/functions/utils.py
JaysAppManager/functions/sql/AppSettings.py
JaysAppManager/functions/sql/__init__.py
JaysAppManager/functions/sql/settings.py
JaysAppManager-0.0.47.dist-info/METADATA
JaysAppManager-0.0.47.dist-info/WHEEL
JaysAppManager-0.0.47.dist-info/entry_points.txt
JaysAppManager-0.0.47.dist-info/top_level.txt
JaysAppManager-0.0.47.dist-info/RECORD
