Metadata-Version: 2.1
Name: JaysAppManager
Version: 0.0.47
Summary: A helpful appmanager
Author: Jay Fesco
Author-email: jayfesco1@gmail.com
License: MIT
Requires-Dist: appwrite
Requires-Dist: python-dotenv
Requires-Dist: redis
Requires-Dist: b2sdk
Requires-Dist: requests
Requires-Dist: openai
Requires-Dist: cryptography
Requires-Dist: langchain
Requires-Dist: langchain-community
Requires-Dist: langchain-core
Requires-Dist: mysql-connector-python
Requires-Dist: certifi >=14.05.14
Requires-Dist: six >=1.10
Requires-Dist: python-dateutil >=2.5.3
Requires-Dist: setuptools >=21.0.0
Requires-Dist: urllib3 >=1.15.1
